AUTHORS
ChangeLog
LICENSE
MANIFEST.in
NOTICE
README.txt
setup.py
lyrical/__init__.py
lyrical/site_calendar/__init__.py
lyrical/site_calendar/admin.py
lyrical/site_calendar/models.py
lyrical/site_calendar/tests.py
lyrical/site_calendar/urls.py
lyrical/site_calendar/views.py
lyrical/site_calendar/templates/admin/site_calendar/change_form.html
lyrical/site_calendar/templates/site_calendar/event_detail.html
lyrical/site_calendar/templates/site_calendar/index_list.html
lyrical/site_content/__init__.py
lyrical/site_content/admin.py
lyrical/site_content/middleware.py
lyrical/site_content/models.py
lyrical/site_content/settings.py
lyrical/site_content/views.py
lyrical/site_content/doc/main.css
lyrical/site_content/doc/main.js
lyrical/site_content/doc/plugins.js
lyrical/site_content/management/__init__.py
lyrical/site_content/management/commands/__init__.py
lyrical/site_content/management/commands/sitecontentcopystatic.py
lyrical/site_content/migrations/0001_initial.py
lyrical/site_content/migrations/__init__.py
lyrical/site_content/south_migrations/0001_initial.py
lyrical/site_content/south_migrations/0002_auto__del_unique_sitepage_url.py
lyrical/site_content/south_migrations/0003_auto__add_field_sitepage_site.py
lyrical/site_content/south_migrations/0004_auto__add_unique_sitepage_url_site.py
lyrical/site_content/south_migrations/0005_auto__add_siteposition.py
lyrical/site_content/south_migrations/0006_auto__add_field_siteposition_css_class.py
lyrical/site_content/south_migrations/0007_auto__add_field_siteblock_css_class.py
lyrical/site_content/south_migrations/0008_auto__add_field_siteblock_siteposition.py
lyrical/site_content/south_migrations/0009_auto__add_field_siteblock_enable_rte.py
lyrical/site_content/south_migrations/0010_auto__add_field_siteblock_weight.py
lyrical/site_content/south_migrations/0011_auto__add_sitepagepositionblock.py
lyrical/site_content/south_migrations/0012_auto__add_field_sitepagepositionblock_siteblocks.py
lyrical_page.egg-info/PKG-INFO
lyrical_page.egg-info/SOURCES.txt
lyrical_page.egg-info/dependency_links.txt
lyrical_page.egg-info/not-zip-safe
lyrical_page.egg-info/requires.txt
lyrical_page.egg-info/top_level.txt