Metadata-Version: 1.1
Name: lyrical-page
Version: 3.1.0
Summary: Website content system based on a mashup of ideas from the Django contrib flatpage appp, joomla!, and many years of systems development..
Home-page: http://www.lyrical.net/projects/lyrical_page/
Author: Will LaShell
Author-email: wlashell@lyrical.net
License: Apache Software License
Platform: UNKNOWN
Classifier: Development Status :: 2 - Pre-Alpha
Classifier: Environment :: Web Environment
Classifier: Intended Audience :: Developers
Classifier: License :: OSI Approved :: Apache Software License
Classifier: Operating System :: OS Independent
Classifier: Programming Language :: Python :: 2.7
Classifier: Framework :: Django :: 1.10
